update_tracker/__init__.py
update_tracker/cli.py
update_tracker/local.py
update_tracker/utils.py
update_tracker/object/__init__.py
update_tracker/object/printer.py
update_tracker/object/update_tracker.py
update_tracker-0.0.3.dist-info/METADATA
update_tracker-0.0.3.dist-info/WHEEL
update_tracker-0.0.3.dist-info/entry_points.txt
update_tracker-0.0.3.dist-info/top_level.txt
update_tracker-0.0.3.dist-info/RECORD
